.gitignore
CHANGES.txt
CONTRIBUTORS.txt
MANIFEST.in
README.rst
bootstrap.py
buildout.cfg
setup.py
collective/__init__.py
collective.js.bootstrap.egg-info/PKG-INFO
collective.js.bootstrap.egg-info/SOURCES.txt
collective.js.bootstrap.egg-info/dependency_links.txt
collective.js.bootstrap.egg-info/entry_points.txt
collective.js.bootstrap.egg-info/namespace_packages.txt
collective.js.bootstrap.egg-info/not-zip-safe
collective.js.bootstrap.egg-info/requires.txt
collective.js.bootstrap.egg-info/top_level.txt
collective/js/__init__.py
collective/js/bootstrap/__init__.py
collective/js/bootstrap/configure.zcml
collective/js/bootstrap/resources/css/bootstrap-theme.css
collective/js/bootstrap/resources/css/bootstrap-theme.css.map
collective/js/bootstrap/resources/css/bootstrap-theme.min.css
collective/js/bootstrap/resources/css/bootstrap-theme.min.css.map
collective/js/bootstrap/resources/css/bootstrap.css
collective/js/bootstrap/resources/css/bootstrap.css.map
collective/js/bootstrap/resources/css/bootstrap.min.css
collective/js/bootstrap/resources/css/bootstrap.min.css.map
collective/js/bootstrap/resources/fonts/glyphicons-halflings-regular.eot
collective/js/bootstrap/resources/fonts/glyphicons-halflings-regular.svg
collective/js/bootstrap/resources/fonts/glyphicons-halflings-regular.ttf
collective/js/bootstrap/resources/fonts/glyphicons-halflings-regular.woff
collective/js/bootstrap/resources/fonts/glyphicons-halflings-regular.woff2
collective/js/bootstrap/resources/js/bootstrap.js
collective/js/bootstrap/resources/js/bootstrap.min.js
collective/js/bootstrap/resources/js/npm.js
docs/LICENSE.GPL
docs/LICENSE.txt