Metadata-Version: 1.1
Name: collective.js.bootstrap
Version: 3.3.6
Summary: Get twitter bootstrap as browser resources
Home-page: https://github.com/collective/collective.js.bootstrap
Author: JeanMichel aka toutpt
Author-email: toutpt@gmail.com
License: gpl
Keywords: plone
Platform: UNKNOWN
Classifier: Environment :: Web Environment
Classifier: License :: OSI Approved :: GNU General Public License (GPL)
Classifier: Operating System :: OS Independent
Classifier: Framework :: Zope2
Classifier: Framework :: Plone
Classifier: Framework :: Plone :: 4.0
Classifier: Framework :: Plone :: 4.1
Classifier: Framework :: Plone :: 4.2
Classifier: Framework :: Plone :: 4.3
Classifier: Programming Language :: Python
Classifier: Programming Language :: Python :: 2.6
Classifier: Programming Language :: Python :: 2.7
